demos/athens-demo.py
demos/small_nbhd_walls.py
demos/solweig_gbg_test.py
demos/data/Goteborg_SWEREF99_1200/CDSM_KRbig.asc
demos/data/Goteborg_SWEREF99_1200/CDSM_KRbig.tif
demos/data/Goteborg_SWEREF99_1200/DEM_KRbig.tif
demos/data/Goteborg_SWEREF99_1200/DSM_KRbig.tif
demos/data/Goteborg_SWEREF99_1200/GBG_TMY_1977.txt
demos/data/Goteborg_SWEREF99_1200/buildings.dbf
demos/data/Goteborg_SWEREF99_1200/buildings.prj
demos/data/Goteborg_SWEREF99_1200/buildings.qpj
demos/data/Goteborg_SWEREF99_1200/buildings.shp
demos/data/Goteborg_SWEREF99_1200/buildings.shx
demos/data/Goteborg_SWEREF99_1200/config_solweig_old_fmt.ini
demos/data/Goteborg_SWEREF99_1200/configsolweig_alt.ini
demos/data/Goteborg_SWEREF99_1200/gbg19970606_2015a.txt
demos/data/Goteborg_SWEREF99_1200/gbg20001219_2015a.txt
demos/data/Goteborg_SWEREF99_1200/landcover.tif
demos/data/Goteborg_SWEREF99_1200/landcoverstyle.qml
demos/data/Goteborg_SWEREF99_1200/mask_layer.geojson
demos/data/Goteborg_SWEREF99_1200/parametersforsolweig.json
demos/data/Goteborg_SWEREF99_1200/poi_gbg.cpg
demos/data/Goteborg_SWEREF99_1200/poi_gbg.dbf
demos/data/Goteborg_SWEREF99_1200/poi_gbg.prj
demos/data/Goteborg_SWEREF99_1200/poi_gbg.qmd
demos/data/Goteborg_SWEREF99_1200/poi_gbg.shp
demos/data/Goteborg_SWEREF99_1200/poi_gbg.shx
demos/data/athens/DEM.tif
demos/data/athens/DSM.tif
demos/data/athens/athens_2023.epw
demos/data/athens/configsolweig.ini
demos/data/athens/parametersforsolweig.json
demos/data/athens/trees.gpkg
demos/data/small_nbhd/dsm.tif
demos/data/small_nbhd/dsm_clipped.tif
deprecated/functions/SOLWEIGpython/solweig_runner_old.py
tests/test_common.py
tests/test_perez.py
umep/class_configs.py
umep/common.py
umep/configsolweig.ini
umep/parametersforsolweig.json
umep/shadow_generator_algorithm.py
umep/skyviewfactor_algorithm.py
umep/solweig_algorithm.py
umep/wall_heightaspect_algorithm.py
umep/functions/dailyshading.py
umep/functions/svf_functions.py
umep/functions/wallalgorithms.py
umep/functions/SOLWEIGpython/CirclePlotBar.py
umep-0.0.1b47.dist-info/licenses/LICENSE
umep-0.0.1b47.dist-info/METADATA
umep-0.0.1b47.dist-info/WHEEL
umep-0.0.1b47.dist-info/top_level.txt
umep-0.0.1b47.dist-info/RECORD
