Metadata-Version: 2.4
Name: umep
Version: 0.0.1b47
Summary: urban multi-scale environmental predictor
Author: UMEP Developers
Maintainer: UMEP Developers
License: AGPL-3.0
Project-URL: homepage, https://github.com/UMEP-dev/umep-core
Project-URL: documentation, https://github.com/UMEP-dev/umep-core
Project-URL: repository, https://github.com/UMEP-dev/umep-core
Keywords: python3,geographical-information-system,spatial-data,spatial-data-analysis,urban-climate,urban-heat-island,urban-meteorology,urban-microclimate,urban-planning,urban-sustainability,urban-thermal-comfort,urban-thermal-environment,urban-thermal-mapping,urban-thermal-modelling,urban-thermal-simulation,urban-thermal-sustainability
Classifier: Programming Language :: Python :: 3.9
Classifier: Programming Language :: Python :: 3.10
Classifier: Programming Language :: Python :: 3.11
Classifier: Programming Language :: Python :: 3.12
Classifier: Programming Language :: Python :: 3.13
Requires-Python: <3.14,>=3.9
License-File: LICENSE
Requires-Dist: geopandas>=1.0.1
Requires-Dist: matplotlib>=3.9.2
Requires-Dist: pandas>=2.2.3
Requires-Dist: pvlib>=0.11.1
Requires-Dist: rasterio>=1.4.1
Requires-Dist: shapely>=2.0.6
Requires-Dist: tqdm>=4.66.5
Requires-Dist: rioxarray>=0.15.0
Requires-Dist: xarray>=2024.7.0
Requires-Dist: scipy>=1.13.1
Requires-Dist: pyproj>=3.6.1
Requires-Dist: numpy>=2.0.2
Dynamic: license-file
